{"id": "json.decoder", "path": "D:\\Anaconda3\\lib\\site-packages\\mypy\\typeshed\\stdlib\\json\\decoder.pyi", "mtime": 1624522122, "size": 1090, "hash": "f39b4e3c5bd7ada52c992816d529fb14fa8a031496c0f6708c067b01ae823053", "data_mtime": 1639480314, "dependencies": ["typing", "builtins", "abc"], "suppressed": [], "options": {"check_untyped_defs": false, "disallow_incomplete_defs": false, "disallow_any_unimported": false, "follow_imports_for_stubs": false, "disallow_subclassing_any": false, "allow_untyped_globals": false, "always_false": [], "disallow_any_explicit": false, "disallow_untyped_calls": false, "allow_redefinition": false, "no_implicit_optional": false, "warn_unused_ignores": false, "mypyc": false, "disallow_untyped_decorators": false, "implicit_reexport": true, "disallow_any_decorated": false, "strict_optional": true, "follow_imports": "silent", "disallow_untyped_defs": false, "ignore_errors": false, "strict_optional_whitelist": null, "warn_unreachable": false, "ignore_missing_imports": true, "warn_no_return": true, "strict_equality": false, "warn_return_any": false, "bazel": false, "local_partial_types": false, "always_true": [], "show_none_errors": true, "platform": "win32", "plugins": [], "disallow_any_expr": false, "disallow_any_generics": false}, "dep_prios": [5, 5, 30], "dep_lines": [1, 1, 1], "interface_hash": "c90c85e145f2f6b6f7e245780c47a4a12446c1686b76f560751658fbce524024", "version_id": "0.910", "ignore_all": true, "plugin_data": null}