{"id": "urllib.parse", "path": "F:\\Anaconda\\anaconda\\lib\\site-packages\\mypy\\typeshed\\stdlib\\urllib\\parse.pyi", "mtime": 1624522122, "size": 5009, "hash": "42db1a4c436c63b660e783719abf25c5c788861ab1fe5a69c6411de1b9886645", "data_mtime": 1639964419, "dependencies": ["sys", "typing", "builtins", "abc"], "suppressed": [], "options": {"strict_optional_whitelist": null, "warn_unreachable": false, "bazel": false, "follow_imports_for_stubs": false, "mypyc": false, "warn_unused_ignores": false, "disallow_any_generics": false, "always_false": [], "strict_equality": false, "local_partial_types": false, "warn_return_any": false, "disallow_untyped_defs": false, "check_untyped_defs": false, "platform": "win32", "plugins": [], "always_true": [], "follow_imports": "silent", "implicit_reexport": true, "ignore_errors": false, "ignore_missing_imports": true, "disallow_any_expr": false, "allow_untyped_globals": false, "no_implicit_optional": false, "warn_no_return": true, "disallow_untyped_calls": false, "disallow_subclassing_any": false, "allow_redefinition": false, "disallow_any_unimported": false, "strict_optional": true, "disallow_any_decorated": false, "disallow_incomplete_defs": false, "disallow_any_explicit": false, "show_none_errors": true, "disallow_untyped_decorators": false}, "dep_prios": [10, 5, 5, 30], "dep_lines": [1, 2, 1, 1], "interface_hash": "bf6a15fa6cc039a3b3fceb864206d11b32885963fbac0bce59f4fb4178c253e5", "version_id": "0.910", "ignore_all": true, "plugin_data": null}